pygeine/__init__.py
pygeine/functions.py
pygeine/functions_test.py
pygeine/plot.py
pygeine/pybasics.py
pygeine-0.0.6.dist-info/METADATA
pygeine-0.0.6.dist-info/WHEEL
pygeine-0.0.6.dist-info/top_level.txt
pygeine-0.0.6.dist-info/RECORD
