Metadata-Version: 2.1
Name: pygeine
Version: 0.0.6
Summary: Learning Python will be fun
Home-page: https://github.com/Mohamedsaad55/Py-Geine
Author: Mohamed Saad
License: MIT
Project-URL: Source, https://github.com/Mohamedsaad55/Py-Geine
Project-URL: Documentation, https://yourusername.github.io/pygeine
Keywords: python learning
Classifier: Development Status :: 3 - Alpha
Classifier: Intended Audience :: Developers
Classifier: License :: OSI Approved :: MIT License
Classifier: Programming Language :: Python :: 3.7
Classifier: Programming Language :: Python :: 3.8
Classifier: Programming Language :: Python :: 3.9
Classifier: Programming Language :: Python :: 3.10
Classifier: Topic :: Software Development :: Libraries :: Python Modules
Classifier: Operating System :: OS Independent
Requires-Dist: numpy
Requires-Dist: pandas
Requires-Dist: ipywidgets
Requires-Dist: seaborn
Requires-Dist: matplotlib
Provides-Extra: jupyter
Requires-Dist: ipykernel ; extra == 'jupyter'
Requires-Dist: matplotlib ; extra == 'jupyter'
